bin2tap_metsuos/__init__.py
bin2tap_metsuos/bin2tap_zxsgm.py
bin2tap_metsuos/cli.py
bin2tap_metsuos-0.3.dist-info/METADATA
bin2tap_metsuos-0.3.dist-info/WHEEL
bin2tap_metsuos-0.3.dist-info/entry_points.txt
bin2tap_metsuos-0.3.dist-info/top_level.txt
bin2tap_metsuos-0.3.dist-info/RECORD
