Metadata-Version: 2.4
Name: bin2tap-metsuos
Version: 0.3
Summary: MetsuOS Version to avoid skooltools bin2tap dep conflict. Convert a binary file into ZX Spectrum TAP file
Home-page: https://github.com/metsuke/bin2tap-py-metsuos
Author: Raül Torralba => Raúl Carrillo aka metsuke
Dynamic: author
Dynamic: description
Dynamic: description-content-type
Dynamic: home-page
Dynamic: summary
